yaml_overlay/__init__.py
yaml_overlay/cli.py
yaml_overlay-0.2.0.dist-info/METADATA
yaml_overlay-0.2.0.dist-info/WHEEL
yaml_overlay-0.2.0.dist-info/entry_points.txt
yaml_overlay-0.2.0.dist-info/licenses/LICENSE
yaml_overlay-0.2.0.dist-info/RECORD
