Metadata-Version: 2.4
Name: yaml-overlay
Version: 0.2.0
Summary: Visualize the provenance of YAML values in a file resulting from an overlay of multiple value files
License: MIT
License-File: LICENSE
Author: Balthazar Rouberol
Author-email: br@imap.cc
Requires-Python: >=3.10
Classifier: License :: OSI Approved :: MIT License
Classifier: Programming Language :: Python :: 3
Classifier: Programming Language :: Python :: 3.10
Classifier: Programming Language :: Python :: 3.11
Classifier: Programming Language :: Python :: 3.12
Classifier: Programming Language :: Python :: 3.13
Classifier: Programming Language :: Python :: 3.14
Requires-Dist: pyyaml (>=6.0.3,<7.0.0)
